{
        "set5": [
                {
                        "sets": ["zonal_mean_xy"],
                        "case_id": "GPCP_v2.2",
                        "variables": ["PRECT"],
                        "ref_name": "GPCP_v2.2",
                        "reference_name": "GPCP (yrs1979-2014)",
                        "seasons": ["ANN", "DJF", "MAM", "JJA", "SON"],
                        "regions": ["global"]
                },

                {
                        "sets": ["zonal_mean_xy"],
                        "case_id": "SST_CL_HadISST",
                        "variables": ["SST"],
                        "ref_name": "HadISST_CL",
                        "reference_name": "HadISST/OI.v2 (Climatology) 1982-2001",
                        "seasons": ["ANN", "DJF", "MAM", "JJA", "SON"]
                },
                {
                        "sets": ["zonal_mean_xy"],
                        "case_id": "SST_PI_HadISST",
                        "variables": ["SST"],
                        "ref_name": "HadISST_PI",
                        "reference_name": "HadISST/OI.v2 (Pre-Indust) 1870-1900",
                        "seasons": ["ANN", "DJF", "MAM", "JJA", "SON"]
                },
                {
                        "sets": ["zonal_mean_xy"],
                        "case_id": "SST_PD_HadISST",
                        "variables": ["SST"],
                        "ref_name": "HadISST_PD",
                        "reference_name": "HadISST/OI.v2 (Present Day) 1999-2008",
                        "seasons": ["ANN", "DJF", "MAM", "JJA", "SON"]
                },
                {
                        "sets": ["zonal_mean_xy"],
                        "case_id": "CERES-EBAF-TOA-v4.0",
                        "variables": ["SOLIN"],
                        "ref_name": "ceres_ebaf_toa_v4.0",
                        "reference_name": "CERES-EBAF 2001-2015",
                        "seasons": ["ANN", "DJF", "MAM", "JJA", "SON"]
                },
                {
                        "sets": ["zonal_mean_xy"],
                        "case_id": "CERES-EBAF-TOA-v4.0",
                        "variables": ["ALBEDO"],
                        "ref_name": "ceres_ebaf_toa_v4.0",
                        "reference_name": "CERES-EBAF 2001-2015",
                        "seasons": ["ANN", "DJF", "MAM", "JJA", "SON"]
                },
                {
                        "sets": ["zonal_mean_xy"],
                        "case_id": "CERES-EBAF-TOA-v4.0",
                        "variables": ["ALBEDOC"],
                        "ref_name": "ceres_ebaf_toa_v4.0",
                        "reference_name": "CERES-EBAF 2001-2015",
                        "seasons": ["ANN", "DJF", "MAM", "JJA", "SON"]
                },
                {
                        "sets": ["zonal_mean_xy"],
                        "case_id": "CERES-EBAF-TOA-v4.0",
                        "variables": ["RESTOM"],
                        "ref_name": "ceres_ebaf_toa_v4.0",
                        "reference_name": "CERES-EBAF 2001-2015",
                        "seasons": ["ANN", "DJF", "MAM", "JJA", "SON"]
                },
                {
                        "sets": ["zonal_mean_xy"],
                        "case_id": "CERES-EBAF-TOA-v4.0",
                        "variables": ["FLUT"],
                        "ref_name": "ceres_ebaf_toa_v4.0",
                        "reference_name": "CERES-EBAF 2001-2015",
                        "seasons": ["ANN", "DJF", "MAM", "JJA", "SON"]
                },
                {
                        "sets": ["zonal_mean_xy"],
                        "case_id": "CERES-EBAF-TOA-v4.0",
                        "variables": ["FLUTC"],
                        "ref_name": "ceres_ebaf_toa_v4.0",
                        "reference_name": "CERES-EBAF 2001-2015",
                        "seasons": ["ANN", "DJF", "MAM", "JJA", "SON"]
                },
                {
                        "sets": ["zonal_mean_xy"],
                        "case_id": "CERES-EBAF-TOA-v4.0",
                        "variables": ["FSNTOA"],
                        "ref_name": "ceres_ebaf_toa_v4.0",
                        "reference_name": "CERES-EBAF 2001-2015",
                        "seasons": ["ANN", "DJF", "MAM", "JJA", "SON"]
                },
                {
                        "sets": ["zonal_mean_xy"],
                        "case_id": "CERES-EBAF-TOA-v4.0",
                        "variables": ["FSNTOAC"],
                        "ref_name": "ceres_ebaf_toa_v4.0",
                        "reference_name": "CERES-EBAF 2001-2015",
                        "seasons": ["ANN", "DJF", "MAM", "JJA", "SON"]
                },
                {
                        "sets": ["zonal_mean_xy"],
                        "case_id": "CERES-EBAF-TOA-v4.0",
                        "variables": ["SWCF"],
                        "ref_name": "ceres_ebaf_toa_v4.0",
                        "reference_name": "CERES-EBAF 2001-2015",
                        "seasons": ["ANN", "DJF", "MAM", "JJA", "SON"]
                },
                {
                        "sets": ["zonal_mean_xy"],
                        "case_id": "CERES-EBAF-TOA-v4.0",
                        "variables": ["LWCF"],
                        "ref_name": "ceres_ebaf_toa_v4.0",
                        "reference_name": "CERES-EBAF 2001-2015",
                        "seasons": ["ANN", "DJF", "MAM", "JJA", "SON"]
                },
                {
                        "sets": ["zonal_mean_xy"],
                        "case_id": "CERES-EBAF-TOA-v4.0",
                        "variables": ["NETCF"],
                        "ref_name": "ceres_ebaf_toa_v4.0",
                        "reference_name": "CERES-EBAF 2001-2015",
                        "seasons": ["ANN", "DJF", "MAM", "JJA", "SON"]
                },
                {
                        "sets": ["zonal_mean_xy"],
                        "case_id": "CERES-EBAF-surface-v4.0",
                        "variables": ["ALBEDO_SRF"],
                        "ref_name": "ceres_ebaf_surface_v4.0",
                        "reference_name": "CERES-EBAF March 2000-AUG 2015",
                        "seasons": ["ANN", "DJF", "MAM", "JJA", "SON"]
                },
                {
                        "sets": ["zonal_mean_xy"],
                        "case_id": "CERES-EBAF-surface-v4.0",
                        "variables": ["SWCFSRF"],
                        "ref_name": "ceres_ebaf_surface_v4.0",
                        "reference_name": "CERES-EBAF March 2000-AUG 2015",
                        "seasons": ["ANN", "DJF", "MAM", "JJA", "SON"]
                },
                {
                        "sets": ["zonal_mean_xy"],
                        "case_id": "CERES-EBAF-surface-v4.0",
                        "variables": ["LWCFSRF"],
                        "ref_name": "ceres_ebaf_surface_v4.0",
                        "reference_name": "CERES-EBAF March 2000-AUG 2015",
                        "seasons": ["ANN", "DJF", "MAM", "JJA", "SON"]
                },
                {
                        "sets": ["zonal_mean_xy"],
                        "case_id": "CERES-EBAF-surface-v4.0",
                        "variables": ["FLDS"],
                        "ref_name": "ceres_ebaf_surface_v4.0",
                        "reference_name": "CERES-EBAF March 2000-AUG 2015",
                        "seasons": ["ANN", "DJF", "MAM", "JJA", "SON"]
                },
                {
                        "sets": ["zonal_mean_xy"],
                        "case_id": "CERES-EBAF-surface-v4.0",
                        "variables": ["FLDSC"],
                        "ref_name": "ceres_ebaf_surface_v4.0",
                        "reference_name": "CERES-EBAF March 2000-AUG 2015",
                        "seasons": ["ANN", "DJF", "MAM", "JJA", "SON"]
                },
                {
                        "sets": ["zonal_mean_xy"],
                        "case_id": "CERES-EBAF-surface-v4.0",
                        "variables": ["FLNS"],
                        "ref_name": "ceres_ebaf_surface_v4.0",
                        "reference_name": "CERES-EBAF March 2000-AUG 2015",
                        "seasons": ["ANN", "DJF", "MAM", "JJA", "SON"]
                },
                {
                        "sets": ["zonal_mean_xy"],
                        "case_id": "CERES-EBAF-surface-v4.0",
                        "variables": ["FLNSC"],
                        "ref_name": "ceres_ebaf_surface_v4.0",
                        "reference_name": "CERES-EBAF March 2000-AUG 2015",
                        "seasons": ["ANN", "DJF", "MAM", "JJA", "SON"]
                },
                {
                        "sets": ["zonal_mean_xy"],
                        "case_id": "CERES-EBAF-surface-v4.0",
                        "variables": ["FSDS"],
                        "ref_name": "ceres_ebaf_surface_v4.0",
                        "reference_name": "CERES-EBAF March 2000-AUG 2015",
                        "seasons": ["ANN", "DJF", "MAM", "JJA", "SON"]
                },
                {
                        "sets": ["zonal_mean_xy"],
                        "case_id": "CERES-EBAF-surface-v4.0",
                        "variables": ["FSDSC"],
                        "ref_name": "ceres_ebaf_surface_v4.0",
                        "reference_name": "CERES-EBAF March 2000-AUG 2015",
                        "seasons": ["ANN", "DJF", "MAM", "JJA", "SON"]
                },
                {
                        "sets": ["zonal_mean_xy"],
                        "case_id": "CERES-EBAF-surface-v4.0",
                        "variables": ["FSNS"],
                        "ref_name": "ceres_ebaf_surface_v4.0",
                        "reference_name": "CERES-EBAF March 2000-AUG 2015",
                        "seasons": ["ANN", "DJF", "MAM", "JJA", "SON"]
                },
                {
                        "sets": ["zonal_mean_xy"],
                        "case_id": "CERES-EBAF-surface-v4.0",
                        "variables": ["FSNSC"],
                        "ref_name": "ceres_ebaf_surface_v4.0",
                        "reference_name": "CERES-EBAF March 2000-AUG 2015",
                        "seasons": ["ANN", "DJF", "MAM", "JJA", "SON"]
                },
                {
                        "sets": ["zonal_mean_xy"],
                        "case_id": "ERA-Interim",
                        "variables": ["LHFLX"],
                        "ref_name": "ERA-Interim",
                        "reference_name": "ERA-Interim Reanalysis 1979-2015",
                        "seasons": ["ANN", "DJF", "MAM", "JJA", "SON"]
                },
                {
                        "sets": ["zonal_mean_xy"],
                        "case_id": "ERA-Interim",
                        "variables": ["PRECT"],
                        "ref_name": "ERA-Interim",
                        "reference_name": "ERA-Interim Reanalysis 1979-2015",
                        "seasons": ["ANN", "DJF", "MAM", "JJA", "SON"]
                },
                {
                        "sets": ["zonal_mean_xy"],
                        "case_id": "ERA-Interim",
                        "variables": ["PREH2O"],
                        "ref_name": "ERA-Interim",
                        "reference_name": "ERA-Interim Reanalysis 1979-2015",
                        "seasons": ["ANN", "DJF", "MAM", "JJA", "SON"]
        },
                {
                        "sets": ["zonal_mean_xy"],
                        "case_id": "ERA-Interim",
                        "variables": ["U"],
                        "ref_name": "ERA-Interim",
                        "reference_name": "ERA-Interim Reanalysis 1979-2015",
                        "seasons": ["ANN", "DJF", "MAM", "JJA", "SON"],
                        "plevs": [850.0, 200.0]
                },
          {
                        "sets": ["zonal_mean_xy"],
                        "case_id": "ERA-Interim",
                        "variables": ["Z3"],
                        "ref_name": "ERA-Interim",
                        "reference_name": "ERA-Interim Reanalysis 1979-2015",
                        "seasons": ["ANN", "DJF", "MAM", "JJA", "SON"],
                        "plevs": [500.0]
                },
                {
                        "sets": ["zonal_mean_xy"],
                        "case_id": "ERA-Interim",
                        "variables": ["T"],
                        "ref_name": "ERA-Interim",
                        "reference_name": "ERA-Interim Reanalysis 1979-2015",
                        "seasons": ["ANN", "DJF", "MAM", "JJA", "SON"],
                        "plevs": [850.0, 200.0]
                },
                {
                        "sets": ["zonal_mean_xy"],
                        "case_id": "MERRA2",
                        "variables": ["PRECT"],
                        "ref_name": "MERRA2",
                        "reference_name": "MERRA2 Reanalysis 1980-2016",
                        "seasons": ["ANN", "DJF", "MAM", "JJA", "SON"]
                },
                {
                        "sets": ["zonal_mean_xy"],
                        "case_id": "MERRA2",
                        "variables": ["PREH2O"],
                        "ref_name": "MERRA2",
                        "reference_name": "MERRA2 Reanalysis 1980-2016",
                        "seasons": ["ANN", "DJF", "MAM", "JJA", "SON"]
        },
                {
                        "sets": ["zonal_mean_xy"],
                        "case_id": "MERRA2",
                        "variables": ["U"],
                        "ref_name": "MERRA2",
                        "reference_name": "MERRA2 Reanalysis 1980-2016",
                        "seasons": ["ANN", "DJF", "MAM", "JJA", "SON"],
                        "plevs": [850, 200.0]
                },
                {
                        "sets": ["zonal_mean_xy"],
                        "case_id": "MERRA2",
                        "variables": ["Z3"],
                        "ref_name": "MERRA2",
                        "reference_name": "MERRA2 Reanalysis 1980-2016",
                        "seasons": ["ANN", "DJF", "MAM", "JJA", "SON"],
                        "plevs": [500.0]
                },
                {
                        "sets": ["zonal_mean_xy"],
                        "case_id": "MERRA2",
                        "variables": ["T"],
                        "ref_name": "MERRA2",
                        "reference_name": "MERRA2 Reanalysis 1980-2016",
                        "seasons": ["ANN", "DJF", "MAM", "JJA", "SON"],
                        "plevs": [850.0, 200.0]
                },
                {
                        "sets": ["zonal_mean_xy"],
                        "case_id": "Cloud ISCCP",
                        "variables": ["CLDTOT_TAU1.3_ISCCP"],
                        "ref_name": "ISCCPCOSP",
                        "reference_name": "ISCCP 1983 Jul-2008 Jun",
                        "seasons": ["ANN", "DJF", "MAM", "JJA", "SON"]
                },
                {
                        "sets": ["zonal_mean_xy"],
                        "case_id": "Cloud ISCCP",
                        "variables": ["CLDTOT_TAU1.3_9.4_ISCCP"],
                        "ref_name": "ISCCPCOSP",
                        "reference_name": "ISCCP 1983 Jul-2008 Jun",
                        "seasons": ["ANN", "DJF", "MAM", "JJA", "SON"]
                },
                {
                        "sets": ["zonal_mean_xy"],
                        "case_id": "Cloud ISCCP",
                        "variables": ["CLDTOT_TAU9.4_ISCCP"],
                        "ref_name": "ISCCPCOSP",
                        "reference_name": "ISCCP 1983 Jul-2008 Jun",
                        "seasons": ["ANN", "DJF", "MAM", "JJA", "SON"]
                },
                {
                        "sets": ["zonal_mean_xy"],
                        "case_id": "Cloud MISR",
                        "variables": ["CLDTOT_TAU1.3_MISR"],
                        "ref_name": "MISRCOSP",
                        "reference_name": "MISR Simulator",
                        "seasons": ["ANN", "DJF", "MAM", "JJA", "SON"]
                },
                {
                        "sets": ["zonal_mean_xy"],
                        "case_id": "Cloud MISR",
                        "variables": ["CLDTOT_TAU1.3_9.4_MISR"],
                        "ref_name": "MISRCOSP",
                        "reference_name": "MISR Simulator",
                        "seasons": ["ANN", "DJF", "MAM", "JJA", "SON"]
                },
                {
                        "sets": ["zonal_mean_xy"],
                        "case_id": "Cloud MISR",
                        "variables": ["CLDTOT_TAU9.4_MISR"],
                        "ref_name": "MISRCOSP",
                        "reference_name": "MISR Simulator",
                        "seasons": ["ANN", "DJF", "MAM", "JJA", "SON"]
                },
                {
                        "sets": ["zonal_mean_xy"],
                        "case_id": "Cloud MISR",
                        "variables": ["CLDLOW_TAU1.3_MISR"],
                        "ref_name": "MISRCOSP",
                        "reference_name": "MISR Simulator",
                        "seasons": ["ANN", "DJF", "MAM", "JJA", "SON"]
                },
                {
                        "sets": ["zonal_mean_xy"],
                        "case_id": "Cloud MISR",
                        "variables": ["CLDLOW_TAU1.3_9.4_MISR"],
                        "ref_name": "MISRCOSP",
                        "reference_name": "MISR Simulator",
                        "seasons": ["ANN", "DJF", "MAM", "JJA", "SON"]
                },
                {
                        "sets": ["zonal_mean_xy"],
                        "case_id": "Cloud MISR",
                        "variables": ["CLDLOW_TAU9.4_MISR"],
                        "ref_name": "MISRCOSP",
                        "reference_name": "MISR Simulator",
                        "seasons": ["ANN", "DJF", "MAM", "JJA", "SON"]
                },
                {
                        "sets": ["zonal_mean_xy"],
                        "case_id": "Cloud MODIS",
                        "variables": ["CLDTOT_TAU1.3_MODIS"],
                        "ref_name": "MODISCOSP",
                        "reference_name": "MODIS Simulator",
                        "seasons": ["ANN", "DJF", "MAM", "JJA", "SON"]
                },
                {
                        "sets": ["zonal_mean_xy"],
                        "case_id": "Cloud MODIS",
                        "variables": ["CLDTOT_TAU1.3_9.4_MODIS"],
                        "ref_name": "MODISCOSP",
                        "reference_name": "MODIS Simulator",
                        "seasons": ["ANN", "DJF", "MAM", "JJA", "SON"]
                },
                {
                        "sets": ["zonal_mean_xy"],
                        "case_id": "Cloud MODIS",
                        "variables": ["CLDTOT_TAU9.4_MODIS"],
                        "ref_name": "MODISCOSP",
                        "reference_name": "MODIS Simulator",
                        "seasons": ["ANN", "DJF", "MAM", "JJA", "SON"]
                },
                {
                        "sets": ["zonal_mean_xy"],
                        "case_id": "Cloud MODIS",
                        "variables": ["CLDHGH_TAU1.3_MODIS"],
                        "ref_name": "MODISCOSP",
                        "reference_name": "MODIS Simulator",
                        "seasons": ["ANN", "DJF", "MAM", "JJA", "SON"]
                },
                {
                        "sets": ["zonal_mean_xy"],
                        "case_id": "Cloud MODIS",
                        "variables": ["CLDHGH_TAU1.3_9.4_MODIS"],
                        "ref_name": "MODISCOSP",
                        "reference_name": "MODIS Simulator",
                        "seasons": ["ANN", "DJF", "MAM", "JJA", "SON"]
                },
                {
                        "sets": ["zonal_mean_xy"],
                        "case_id": "Cloud MODIS",
                        "variables": ["CLDHGH_TAU9.4_MODIS"],
                        "ref_name": "MODISCOSP",
                        "reference_name": "MODIS Simulator",
                        "seasons": ["ANN", "DJF", "MAM", "JJA", "SON"]
                },
                {
                        "sets": ["zonal_mean_xy"],
                        "case_id": "Cloud Calipso",
                        "variables": ["CLDHGH_CAL"],
                        "ref_name": "CALIPSOCOSP",
                        "reference_name": "CALIPSO-GOCCP Jan2007-Jan2010",
                        "seasons": ["ANN", "DJF", "MAM", "JJA", "SON"]
                },
                {
                        "sets": ["zonal_mean_xy"],
                        "case_id": "Cloud Calipso",
                        "variables": ["CLDLOW_CAL"],
                        "ref_name": "CALIPSOCOSP",
                        "reference_name": "CALIPSO-GOCCP Jan2007-Jan2010",
                        "seasons": ["ANN", "DJF", "MAM", "JJA", "SON"]
                },
                {
                        "sets": ["zonal_mean_xy"],
                        "case_id": "Cloud Calipso",
                        "variables": ["CLDMED_CAL"],
                        "ref_name": "CALIPSOCOSP",
                        "reference_name": "CALIPSO-GOCCP Jan2007-Jan2010",
                        "seasons": ["ANN", "DJF", "MAM", "JJA", "SON"]
                },
                {
                        "sets": ["zonal_mean_xy"],
                        "case_id": "Cloud Calipso",
                        "variables": ["CLDTOT_CAL"],
                        "ref_name": "CALIPSOCOSP",
                        "reference_name": "CALIPSO-GOCCP Jan2007-Jan2010",
                        "seasons": ["ANN", "DJF", "MAM", "JJA", "SON"]
                },
                {
                        "sets": ["zonal_mean_xy"],
                        "case_id": "Cloud SSM/I",
                        "variables": ["TGCLDLWP_OCN"],
                        "ref_name": "SSMI",
                        "reference_name": "SSM/I (Wentz) 1987-2000",
                        "seasons": ["ANN", "DJF", "MAM", "JJA", "SON"]
                }

        ]
}
