<?xml version="1.0"?>

<compsets>

  <help>

    =========================================
    compset naming convention
    =========================================
    The compset longname below has the specified order
    atm, lnd, ice, ocn, river, glc wave model-options

    The notation for the compset longname is
    TIME_ATM[%phys]_LND[%phys]_ICE[%phys]_OCN[%phys]_ROF[%phys]_GLC[%phys]_WAV[%phys][_ESP%phys][_BGC%phys]
    Where for the CAM specific compsets below the following is supported
    TIME = Time period (e.g. 2000, HIST, RCP8...)
    ATM  = [CAM4, CAM5, SATM]
    LND  = [CLM40, CLM45, CLM50, SLND]
    ICE  = [MPASCICE, CICE, DICE, SICE]
    OCN  = [MPASO, DOCN, ,AQUAP, SOCN]
    ROF  = [RTM, MOSART, SROF]
    GLC  = [MPASLISIA, MPASLIALB, CISM1, CISM2, SGLC]
    WAV  = [WW3, DWAV, XWAV, SWAV]
    ESP  = [SESP]
    BGC  = optional BGC scenario

    The OPTIONAL %phys attributes specify submodes of the given system
    For example DOCN%DOM is the data ocean model for DOCN
    ALL the possible %phys choices for each component are listed
    with the -list command for create_newcase
    ALL data models must have a %phys option that corresponds to the data  model mode

    Each compset node is associated with the following elements
    - lname
    - alias
    - support  (optional description of the support level for this compset)
    Each compset node can also have the following attributes
    - grid  (optional regular expression match for grid to work with the compset)

  </help>

  <compset>
    <alias>F1850</alias>
    <lname>1850_CAM4_CLM40%SP_CICE%PRES_DOCN%DOM_RTM_SGLC_SWAV</lname>
  </compset>

  <compset>
    <alias>F1850C5</alias>
    <lname>1850_CAM5_CLM40%SP_CICE%PRES_DOCN%DOM_RTM_SGLC_SWAV</lname>
  </compset>

  <compset>
    <alias>F1850C5L45BGC</alias>
    <lname>1850_CAM5_CLM45%BGC_CICE%PRES_DOCN%DOM_RTM_SGLC_SWAV</lname>
  </compset>

  <compset>
    <alias>F</alias>
    <lname>2000_CAM4_CLM40%SP_CICE%PRES_DOCN%DOM_RTM_SGLC_SWAV</lname>
  </compset>

  <compset>
    <alias>FC5</alias>
    <lname>2000_CAM5_CLM40%SP_CICE%PRES_DOCN%DOM_RTM_SGLC_SWAV</lname>
  </compset>

  <compset>
    <alias>FC5MAM4</alias>
    <lname>2000_CAM5%MAM4_CLM40%SP_CICE%PRES_DOCN%DOM_RTM_SGLC_SWAV</lname>
  </compset>

  <compset>
    <alias>FC5PLMOD</alias>
    <lname>2000_CAM5%MAM4%PLMOD_CLM40%SP_CICE%PRES_DOCN%DOM_RTM_SGLC_SWAV</lname>
  </compset>

  <compset>
    <alias>FC5RESUS</alias>
    <lname>2000_CAM5%MAM4%RESUS_CLM40%SP_CICE%PRES_DOCN%DOM_RTM_SGLC_SWAV</lname>
  </compset>

  <compset>
    <alias>FC5ATMMOD</alias>
    <lname>2000_CAM5%ATMMOD_CLM45%SPBC_CICE%PRES_DOCN%DOM_RTM_SGLC_SWAV</lname>
  </compset>

  <compset>
    <alias>FC5AV1C</alias>
    <lname>2000_CAM5%AV1C_CLM45%SPBC_CICE%PRES_DOCN%DOM_RTM_SGLC_SWAV</lname>
  </compset>

  <compset>
    <alias>FC5AV1C-00</alias>
    <lname>2000_CAM5%AV1C-00_CLM45%SPBC_CICE%PRES_DOCN%DOM_RTM_SGLC_SWAV</lname>
  </compset>

  <compset>
    <alias>F1850C5AV1C-01</alias>
    <lname>1850_CAM5%AV1C-01_CLM45%SPBC_CICE%PRES_DOCN%DOM_RTM_SGLC_SWAV</lname>
  </compset>

  <compset>
    <alias>F1850C5AV1C-02</alias>
    <lname>1850_CAM5%AV1C-02_CLM45%SPBC_CICE%PRES_DOCN%DOM_RTM_SGLC_SWAV</lname>
  </compset>

  <compset>
    <alias>F1850C5AV1C-03</alias>
    <lname>1850_CAM5%AV1C-03_CLM45%SPBC_CICE%PRES_DOCN%DOM_RTM_SGLC_SWAV</lname>
  </compset>

  <compset>
    <alias>F1850C5AV1C-04</alias>
    <lname>1850_CAM5%AV1C-04_CLM45%SPBC_CICE%PRES_DOCN%DOM_RTM_SGLC_SWAV</lname>
  </compset>
  
  <compset>
    <alias>F1850C5AV1C-04P</alias>
    <lname>1850_CAM5%AV1C-04P_CLM45%SPBC_CICE%PRES_DOCN%DOM_RTM_SGLC_SWAV</lname>
  </compset>

  <compset>
    <alias>F1850C5AV1C-L</alias>
    <lname>1850_CAM5%AV1C-L_CLM45%SPBC_CICE%PRES_DOCN%DOM_RTM_SGLC_SWAV</lname>
  </compset>

  <compset>
    <alias>FC5AV1C-01</alias>
    <lname>2000_CAM5%AV1C-01_CLM45%SPBC_CICE%PRES_DOCN%DOM_RTM_SGLC_SWAV</lname>
  </compset>

  <compset>
    <alias>FC5AV1C-02</alias>
    <lname>2000_CAM5%AV1C-02_CLM45%SPBC_CICE%PRES_DOCN%DOM_RTM_SGLC_SWAV</lname>
  </compset>

  <compset>
    <alias>FC5AV1C-03</alias>
    <lname>2000_CAM5%AV1C-03_CLM45%SPBC_CICE%PRES_DOCN%DOM_RTM_SGLC_SWAV</lname>
  </compset>

  <compset>
    <alias>FC5AV1C-04</alias>
    <lname>2000_CAM5%AV1C-04_CLM45%SPBC_CICE%PRES_DOCN%DOM_RTM_SGLC_SWAV</lname>
  </compset>

  <compset>
    <alias>FC5AV1C-04P</alias>
    <lname>2000_CAM5%AV1C-04P_CLM45%SPBC_CICE%PRES_DOCN%DOM_RTM_SGLC_SWAV</lname>
  </compset>

  <compset>
    <alias>FC5AV1C-L</alias>
    <lname>2000_CAM5%AV1C-L_CLM45%SPBC_CICE%PRES_DOCN%DOM_RTM_SGLC_SWAV</lname>
  </compset>

  <compset>
    <alias>FC5AV1F</alias>
    <lname>2000_CAM5%AV1F_CLM45%SPBC_CICE%PRES_DOCN%DOM_RTM_SGLC_SWAV</lname>
  </compset>

  <compset>
    <alias>FC5AV1F-00</alias>
    <lname>2000_CAM5%AV1F-00_CLM45%SPBC_CICE%PRES_DOCN%DOM_RTM_SGLC_SWAV</lname>
  </compset>

  <compset>
    <alias>FC5AV1F-01</alias>
    <lname>2000_CAM5%AV1F-01_CLM45%SPBC_CICE%PRES_DOCN%DOM_RTM_SGLC_SWAV</lname>
  </compset>

  <compset>
   <alias>F20TRC5AV1C-03</alias>
   <lname>20TR_CAM5%AV1C-03_CLM45%SPBC_CICE%PRES_DOCN%DOM_RTM_SGLC_SWAV</lname>
  </compset>

  <compset>
   <alias>F20TRC5AV1C-04</alias>
   <lname>20TR_CAM5%AV1C-04_CLM45%SPBC_CICE%PRES_DOCN%DOM_RTM_SGLC_SWAV</lname>
  </compset>

  <compset>
   <alias>F20TRC5AV1C-04P</alias>
   <lname>20TR_CAM5%AV1C-04P_CLM45%SPBC_CICE%PRES_DOCN%DOM_RTM_SGLC_SWAV</lname>
  </compset>

  <compset>
   <alias>F20TRC5AV1C-L</alias>
   <lname>20TR_CAM5%AV1C-L_CLM45%SPBC_CICE%PRES_DOCN%DOM_RTM_SGLC_SWAV</lname>
  </compset>

  <compset>
    <alias>FC5ATMMODCOSP</alias>
    <lname>2000_CAM5%ATMMODCOSP_CLM45%SPBC_CICE%PRES_DOCN%DOM_RTM_SGLC_SWAV</lname>
  </compset>

  <compset>
    <alias>FC5COSP</alias>
    <lname>2000_CAM5%COSP_CLM40%SP_CICE%PRES_DOCN%DOM_RTM_SGLC_SWAV</lname>
  </compset>

  <compset>
    <alias>FC5UNI</alias>
    <lname>2000_CAM5%UNI_CLM40%SP_CICE%PRES_DOCN%DOM_RTM_SGLC_SWAV</lname>
  </compset>

  <compset>
    <alias>FAMIP</alias>
    <lname>AMIP_CAM4_CLM40%SP_CICE%PRES_DOCN%DOM_RTM_SGLC_SWAV</lname>
  </compset>

  <compset>
    <alias>FAMIPC5</alias>
    <lname>AMIP_CAM5_CLM40%SP_CICE%PRES_DOCN%DOM_RTM_SGLC_SWAV</lname>
  </compset>

  <compset>
    <alias>FAMIPC5UNI</alias>
    <lname>AMIP_CAM5%UNI_CLM40%SP_CICE%PRES_DOCN%DOM_RTM_SGLC_SWAV</lname>
  </compset>

  <compset>
    <alias>FAMIPC5L60</alias>
    <lname>AMIP_CAM5%L60_CLM40%SP_CICE%PRES_DOCN%DOM_RTM_SGLC_SWAV</lname>
  </compset>

  <compset>
    <alias>F1850PDC5</alias>
    <lname>PIPD_CAM5_CLM40%SP_CICE%PRES_DOCN%DOM_RTM_SGLC_SWAV</lname>
  </compset>

  <compset>
    <alias>F1850PDC5L45BGC</alias>
    <lname>20TR_CAM5_CLM45%BGC_CICE%PRES_DOCN%DOM_RTM_SGLC_SWAV</lname>
  </compset>

  <compset>
    <alias>FCN</alias>
    <lname>2000_CAM4_CLM40%CN_CICE%PRES_DOCN%DOM_RTM_SGLC_SWAV</lname>
  </compset>

  <compset>
    <alias>FC5L45BGC</alias>
    <lname>2000_CAM5_CLM45%BGC_CICE%PRES_DOCN%DOM_RTM_SGLC_SWAV</lname>
  </compset>

  <compset>
    <alias>FAMIPCN</alias>
    <lname>AMIP_CAM4_CLM40%CN_CICE%PRES_DOCN%DOM_RTM_SGLC_SWAV</lname>
  </compset>

  <compset>
    <alias>FAMIPC5CN</alias>
    <lname>AMIP_CAM5_CLM40%CN_CICE%PRES_DOCN%DOM_RTM_SGLC_SWAV</lname>
  </compset> 

  <compset>
    <alias>F20TRCN</alias>
    <lname>20TR_CAM4_CLM40%CN_CICE%PRES_DOCN%DOM_RTM_SGLC_SWAV</lname>
  </compset>

  <compset>
    <alias>FC5CLUBB</alias>
    <lname>2000_CAM5%CLB_CLM40%SP_CICE%PRES_DOCN%DOM_RTM_SGLC_SWAV</lname>
  </compset>

  <compset>
    <alias>FC5MG2</alias>
    <lname>2000_CAM5%MG2_CLM40%SP_CICE%PRES_DOCN%DOM_RTM_SGLC_SWAV</lname>
  </compset>

  <compset>
    <alias>FC5CLBMG2</alias>
    <lname>2000_CAM5%CLBMG2_CLM40%SP_CICE%PRES_DOCN%DOM_RTM_SGLC_SWAV</lname>
  </compset>

  <compset>
    <alias>FC5CLBMG2L72</alias>
    <lname>2000_CAM5%CLBMG2L72_CLM40%SP_CICE%PRES_DOCN%DOM_RTM_SGLC_SWAV</lname>
  </compset>

  <compset>
    <alias>FC5CLBMG2BCL72</alias>
    <lname>2000_CAM5%CLBMG2L72_CLM45%SPBC_CICE%PRES_DOCN%DOM_RTM_SGLC_SWAV</lname>
  </compset>

  <compset>
    <alias>FC5CLBMG2LINMAM4RESUSBC</alias>
    <lname>2000_CAM5%CLBMG2LINMAM4RESUS_CLM45%SPBC_CICE%PRES_DOCN%DOM_RTM_SGLC_SWAV</lname>
  </compset>

  <compset>
    <alias>FC5CLBMG2LINMAM4RESUSMOM</alias>
    <lname>2000_CAM5%CLBMG2LINMAM4RESUSMOM_CLM40%SP_CICE%PRES_DOCN%DOM_RTM_SGLC_SWAV</lname>
  </compset>

  <compset>
    <alias>FC5CLBMG2MAM4MOM</alias>
    <lname>2000_CAM5%CLBMG2MAM4MOM_CLM40%SP_CICE%PRES_DOCN%DOM_RTM_SGLC_SWAV</lname>
  </compset>

  <compset>
    <alias>FC5CLBMG2MAM4</alias>
    <lname>2000_CAM5%CLBMG2MAM4_CLM40%SP_CICE%PRES_DOCN%DOM_RTM_SGLC_SWAV</lname>
  </compset>

  <compset>
    <alias>FC5CLBMG2MAM4RESUS</alias>
    <lname>2000_CAM5%CLBMG2MAM4RESUS_CLM40%SP_CICE%PRES_DOCN%DOM_RTM_SGLC_SWAV</lname>
  </compset>

  <compset>
    <alias>FC5CLBMG2MAM4RESUSMOM</alias>
    <lname>2000_CAM5%CLBMG2MAM4RESUSMOM_CLM40%SP_CICE%PRES_DOCN%DOM_RTM_SGLC_SWAV</lname>
  </compset>

  <compset>
    <alias>FC5CLBMG2MAM4RESUSCOSP</alias>
    <lname>2000_CAM5%CLBMG2MAM4RESUSCOSP_CLM40%SP_CICE%PRES_DOCN%DOM_RTM_SGLC_SWAV</lname>
  </compset>

  <compset>
    <alias>FC5CLBMG2MAM4RESUSMOMCOSP</alias>
    <lname>2000_CAM5%CLBMG2MAM4RESUSMOMCOSP_CLM40%SP_CICE%PRES_DOCN%DOM_RTM_SGLC_SWAV</lname>
  </compset>

  <compset>
    <alias>FC5CLBMG2MAM4RESUSBC</alias>
    <lname>2000_CAM5%CLBMG2MAM4RESUS_CLM45%SPBC_CICE%PRES_DOCN%DOM_RTM_SGLC_SWAV</lname>
  </compset>

  <compset>
    <alias>FC5CLBMG2MAM4RESUSMOMBC</alias>
    <lname>2000_CAM5%CLBMG2MAM4RESUSMOM_CLM45%SPBC_CICE%PRES_DOCN%DOM_RTM_SGLC_SWAV</lname>
  </compset>

  <compset>
    <alias>FC5CLBMG2MAM4RESUSCOSPBC</alias>
    <lname>2000_CAM5%CLBMG2MAM4RESUSCOSP_CLM45%SPBC_CICE%PRES_DOCN%DOM_RTM_SGLC_SWAV</lname>
  </compset>

  <compset>
    <alias>FC5CLBMG2MAM4RESUSMOMCOSPBC</alias>
    <lname>2000_CAM5%CLBMG2MAM4RESUSMOMCOSP_CLM45%SPBC_CICE%PRES_DOCN%DOM_RTM_SGLC_SWAV</lname>
  </compset>

  <compset>
    <alias>FC5CLBMG2LINMAM4RESUSMOMCOSPBC</alias>
    <lname>2000_CAM5%CLBMG2MAM4RESUSMOMCOSP_CLM45%SPBC_CICE%PRES_DOCN%DOM_RTM_SGLC_SWAV</lname>
  </compset>

  <compset>
    <alias>F1850C5PM</alias>
    <lname>1850_CAM5%PM_CLM40%SP_CICE%PRES_DOCN%DOM_RTM_SGLC_SWAV</lname>
  </compset>

  <compset>
    <alias>FC5PM</alias>
    <lname>2000_CAM5%PM_CLM40%SP_CICE%PRES_DOCN%DOM_RTM_SGLC_SWAV</lname>
  </compset>

  <compset>
    <alias>F1850W</alias>
    <lname>1850_CAM4%WCCM_CLM40%SP_CICE%PRES_DOCN%DOM_RTM_SGLC_SWAV</lname>
  </compset>

  <compset>
    <alias>FMOZ</alias>
    <lname>2000_CAM4%TMOZ_CLM40%SP_CICE%PRES_DOCN%DOM_RTM_SGLC_SWAV</lname>
  </compset>

  <compset>
    <alias>FW</alias>
    <lname>2000_CAM4%WCCM_CLM40%SP_CICE%PRES_DOCN%DOM_RTM_SGLC_SWAV</lname>
  </compset>

  <compset>
    <alias>FWSC</alias>
    <lname>2000_CAM4%WCSC_CLM40%SP_CICE%PRES_DOCN%DOM_RTM_SGLC_SWAV</lname>
  </compset>

  <compset>
    <alias>FWX</alias>
    <lname>2000_CAM4%WCMX_CLM40%SP_CICE%PRES_DOCN%DOM_RTM_SGLC_SWAV</lname>
  </compset>

  <compset>
    <alias>FWX1996</alias>
    <lname>1996_CAM4%WCMX_CLM40%SP_CICE%PRES_DOCN%DOM_RTM_SGLC_SWAV</lname>
  </compset>

  <compset>
    <alias>FW5</alias>
    <lname>2000_CAM5%WCCM_CLM40%SP_CICE%PRES_DOCN%DOM_RTM_SGLC_SWAV</lname>
  </compset>

  <compset>
    <alias>FMOZSOA</alias>
    <lname>2000_CAM4%MOZS_CLM40%SP_CICE%PRES_DOCN%DOM_RTM_SGLC_SWAV</lname>
  </compset>

  <compset>
    <alias>FSSOA</alias>
    <lname>2000_CAM4%SSOA_CLM40%SP_CICE%PRES_DOCN%DOM_RTM_SGLC_SWAV</lname>
  </compset>

  <compset>
    <alias>F1850CNCHM</alias>
    <lname>1850_CAM4%FCHM_CLM40%CN_CICE%PRES_DOCN%DOM_RTM_SGLC_SWAV</lname>
  </compset>

  <compset>
    <alias>FMOZMAM</alias>
    <lname>2000_CAM5%MOZM_CLM40%CN_CICE%PRES_DOCN%DOM_RTM_SGLC_SWAV</lname>
  </compset>

  <compset>
    <alias>FSTRATMAM3</alias>
    <lname>2000_CAM5%SMA3_CLM40%CN_CICE%PRES_DOCN%DOM_RTM_SGLC_SWAV</lname>
  </compset>

  <compset>
    <alias>FSTRATMAM7</alias>
    <lname>2000_CAM5%SMA7_CLM40%CN_CICE%PRES_DOCN%DOM_RTM_SGLC_SWAV</lname>
  </compset>

  <compset>
    <alias>F55WCN</alias>
    <lname>5505_CAM4%WCCM_CLM40%CN_CICE%PRES_DOCN%DOM_RTM_SGLC_SWAV</lname>
  </compset>

  <compset>
    <alias>FSDW</alias>
    <lname>GEOS_CAM4%WCCM_CLM40%CN_CICE%PRES_DOCN%DOM_RTM_SGLC_SWAV</lname>
  </compset>

  <compset>
    <alias>FSDWSF</alias>
    <lname>GEOS_CAM4%WCSF_CLM40%CN_CICE%PRES_DOCN%DOM_RTM_SGLC_SWAV</lname>
  </compset>

  <compset>
    <alias>FSDCHM</alias>
    <lname>GEOS_CAM4%TMOZ_CLM40%CN_CICE%PRES_DOCN%DOM_RTM_SGLC_SWAV</lname>
  </compset>

  <compset>
    <alias>FSDBAM</alias>
    <lname>GEOS_CAM4%TBAM_CLM40%CN_CICE%PRES_DOCN%DOM_RTM_SGLC_SWAV</lname>
  </compset>

  <compset>
    <alias>FSDSSOA</alias>
    <lname>GEOS_CAM4%SSOA_CLM40%CN_CICE%PRES_DOCN%DOM_RTM_SGLC_SWAV</lname>
  </compset>

  <compset>
    <alias>FSDSMAM</alias>
    <lname>GEOS_CAM5%SMA3_CLM40%SP_CICE%PRES_DOCN%DOM_RTM_SGLC_SWAV</lname>
  </compset>

  <compset>
    <alias>FSCM4A95</alias>
    <lname>AR95_CAM4%SCAM_CLM40%SP_CICE%PRES_DOCN%DOM_RTM_SGLC_SWAV</lname>
  </compset>

  <compset>
    <alias>FSCM5A97</alias>
    <lname>AR97_CAM5%SCAM_CLM40%SP_CICE%PRES_DOCN%DOM_RTM_SGLC_SWAV</lname>
  </compset>


  <compset>
    <alias>FC4AQUAP</alias>
    <lname>2000_CAM4_SLND_SICE_AQUAP_SROF_SGLC_SWAV</lname>
  </compset>

  <compset>
    <alias>FC5AQUAP</alias>
    <lname>2000_CAM5_SLND_SICE_AQUAP_SROF_SGLC_SWAV</lname>
  </compset>

  <compset>
    <alias>FIDEAL</alias>
    <lname>2000_CAM%IDEAL_SLND_SICE_SOCN_SROF_SGLC_SWAV</lname>
  </compset>

  <compset>
    <alias>FADIAB</alias>
    <lname>2000_CAM%ADIAB_SLND_SICE_SOCN_SROF_SGLC_SWAV</lname>
  </compset>

  <!-- FG compsets -->

  <compset>
    <alias>FGCN</alias>
    <lname>2000_CAM4_CLM40%CN_CICE%PRES_DOCN%DOM_RTM_CISM1_SWAV</lname>
  </compset>

  <compset>
    <alias>FG1850CN</alias>
    <lname>1850_CAM4_CLM40%CN_CICE%PRES_DOCN%DOM_RTM_CISM1_SWAV</lname>
  </compset> 	 

  <compset>
    <alias>FGCNIS2</alias>
    <lname>2000_CAM4_CLM40%CN_CICE%PRES_DOCN%DOM_RTM_CISM2P_SWAV</lname>
  </compset>

  <compset>
    <alias>FG20TRCN</alias>
    <lname>20TR_CAM4_CLM40%CN_CICE%PRES_DOCN%DOM_RTM_CISM1_SWAV</lname>
  </compset>

  <entries>

    <entry id="RUN_STARTDATE"> 
      <values>
	<value  compset="AMIP_CAM">1979-01-01</value> 
	<value  compset="HIST_CAM">1850-01-01</value> 
	<value  compset="PIPD_CAM">1850-01-01</value> 
	<value  compset="7905_CAM">1979-01-01</value>
	<value  compset="5505_CAM">1955-01-01</value> 
	<value  compset="1996_CAM\d+%WCMX">1996-01-01</value>
	<value  compset="2000_CAM\d+%WCMX">2000-01-01</value>
	<value  compset="2000_CAM\d+%WCXI">2000-01-01</value>
	<value  compset="2013_CAM\d+%WCBC">2013-01-01</value> 
	<value  compset="GEOS_CAM\d+%WCCM">2005-01-01</value> 
	<value  compset="GEOS_CAM\d+%WTSM">1990-01-01</value> 
	<value  compset="GEOS_CAM\d+%WCSF">2010-01-01</value> 
	<value  compset="GEOS_CAM\d+%TMOZ">2008-01-01</value> 
	<value  compset="GEOS_CAM\d+%TBAM">2008-01-01</value>
	<value  compset="GEOS_CAM\d+%S">2005-01-01</value>
	<value  compset="RCP[2468]_CAM\d+">2005-01-01</value>
	<value  compset="C2R[68]_CAM">1950-01-01</value> 
	<value  compset="C2R4_CAM">2004-01-01</value>
	<value  compset="AR95_CAM">1995-07-18</value>
	<value  compset="AR97_CAM">1997-06-18</value>
      </values>
    </entry>

    <entry id="CALENDAR"> 
      <values>
	<value  compset="GEOS_">GREGORIAN</value>
      </values>
    </entry>

    <entry id="START_TOD"> 
      <values>
	<value  compset="AR95_CAM">19800</value>
	<value  compset="AR97_CAM">84585</value>
      </values>
    </entry>

    <entry id="RUN_TYPE"> 
      <values>
	<value grid="a%0.9x1.25_l%0.9x1.25_oi%0.9x1.25_r%r05_m%gx1v6"	compset="AMIP_CAM50_CLM40%SP_CICE%PRES_DOCN%DOM_RTM_SGLC_SWAV"	 >hybrid</value>
	<value grid="a%0.9x1.25_l%0.9x1.25_oi%0.9x1.25_r%r05_m%gx1v6"	compset="PIPD_CAM50_CLM40%SP_CICE%PRES_DOCN%DOM_RTM_SGLC_SWAV"	 >hybrid</value>
	<value grid="a%ne30np4_l%ne30np4_oi%ne30np4_r%r05_m%gx1v6"	compset="AMIP_CAM50_CLM40%SP_CICE%PRES_DOCN%DOM_RTM_SGLC_SWAV"	 >hybrid</value>
	<value grid="a%ne30np4_l%ne30np4_oi%ne30np4_r%r05_m%gx1v6"	compset="AMIP_CAM50%L60_CLM40%SP_CICE%PRES_DOCN%DOM_RTM_SGLC_SWAV">hybrid</value>
	<value grid="a%ne30np4_l%ne30np4_oi%ne30np4_r%r05_m%gx1v6"	compset="PIPD_CAM50_CLM40%SP_CICE%PRES_DOCN%DOM_RTM_SGLC_SWAV"	 >hybrid</value>
	<value grid="a%0.9x1.25_l%0.9x1.25_oi%0.9x1.25_r%r05_m%gx1v6"	compset="AMIP_CAM40_CLM40%SP_CICE%PRES_DOCN%DOM_RTM_SGLC_SWAV"	 >hybrid</value>
	<value grid="a%1.9x2.5_l%1.9x2.5_oi%1.9x2.5_r%r05_m%gx1v6"	compset="AMIP_CAM50_CLM40%SP_CICE%PRES_DOCN%DOM_RTM_SGLC_SWAV"	 >hybrid</value>
	<value grid="a%1.9x2.5_l%1.9x2.5_oi%1.9x2.5_r%r05_m%gx1v6"	compset="AMIP_CAM40_CLM40%CN_CICE%PRES_DOCN%DOM_RTM_SGLC_SWAV"	 >hybrid</value>
      </values>
    </entry>

    <entry id="RUN_REFCASE"> 
      <values>
	<value grid="a%0.9x1.25_l%0.9x1.25_oi%0.9x1.25_r%r05_m%gx1v6"	compset="AMIP_CAM50_CLM40%SP_CICE%PRES_DOCN%DOM_RTM_SGLC_SWAV"	 >b40_20th_1d_b08c5cn_139jp</value>   
	<value grid="a%0.9x1.25_l%0.9x1.25_oi%0.9x1.25_r%r05_m%gx1v6"	compset="PIPD_CAM50_CLM40%SP_CICE%PRES_DOCN%DOM_RTM_SGLC_SWAV"	 >b40_20th_1d_b08c5cn_139jp</value>   
	<value grid="a%ne30np4_l%ne30np4_oi%ne30np4_r%r05_m%gx1v6"	compset="AMIP_CAM50_CLM40%SP_CICE%PRES_DOCN%DOM_RTM_SGLC_SWAV"	 >f.e12.FAMIPC5.ne30_ne30.amip_L30.001</value>   
	<value grid="a%ne30np4_l%ne30np4_oi%ne30np4_r%r05_m%gx1v6"	compset="AMIP_CAM50%L60_CLM40%SP_CICE%PRES_DOCN%DOM_RTM_SGLC_SWAV">f.e12.FAMIPC5.ne30_ne30.amip_L60.001</value>   
	<value grid="a%ne30np4_l%ne30np4_oi%ne30np4_r%r05_m%gx1v6"	compset="PIPD_CAM50_CLM40%SP_CICE%PRES_DOCN%DOM_RTM_SGLC_SWAV"	 >f.e12.FAMIPC5.ne30_ne30.amip_L30.001</value>   
	<value grid="a%0.9x1.25_l%0.9x1.25_oi%0.9x1.25_r%r05_m%gx1v6"	compset="AMIP_CAM40_CLM40%SP_CICE%PRES_DOCN%DOM_RTM_SGLC_SWAV"	 >b40.20th.track1.1deg.004</value>   
	<value grid="a%1.9x2.5_l%1.9x2.5_oi%1.9x2.5_r%r05_m%gx1v6"	compset="AMIP_CAM50_CLM40%SP_CICE%PRES_DOCN%DOM_RTM_SGLC_SWAV"	 >b40_20th_2d_r07c5cn_161jp</value>   
	<value grid="a%1.9x2.5_l%1.9x2.5_oi%1.9x2.5_r%r05_m%gx1v6"	compset="AMIP_CAM40_CLM40%CN_CICE%PRES_DOCN%DOM_RTM_SGLC_SWAV"	 >b40.20th.track1.2deg.001</value > 
      </values>
    </entry>

    <entry id="RUN_REFDATE">
      <values>
	<value grid="a%0.9x1.25_l%0.9x1.25_oi%0.9x1.25_r%r05_m%gx1v6"	compset="AMIP_CAM50_CLM40%SP_CICE%PRES_DOCN%DOM_RTM_SGLC_SWAV"	 >1979-01-01</value>   
	<value grid="a%0.9x1.25_l%0.9x1.25_oi%0.9x1.25_r%r05_m%gx1v6"	compset="PIPD_CAM50_CLM40%SP_CICE%PRES_DOCN%DOM_RTM_SGLC_SWAV"	 >1979-01-01</value>   
	<value grid="a%ne30np4_l%ne30np4_oi%ne30np4_r%r05_m%gx1v6"	compset="AMIP_CAM50_CLM40%SP_CICE%PRES_DOCN%DOM_RTM_SGLC_SWAV"	 >1979-01-01</value>   
	<value grid="a%ne30np4_l%ne30np4_oi%ne30np4_r%r05_m%gx1v6"	compset="AMIP_CAM50%L60_CLM40%SP_CICE%PRES_DOCN%DOM_RTM_SGLC_SWAV">1979-01-01</value>   
	<value grid="a%ne30np4_l%ne30np4_oi%ne30np4_r%r05_m%gx1v6"	compset="PIPD_CAM50_CLM40%SP_CICE%PRES_DOCN%DOM_RTM_SGLC_SWAV"	 >1979-01-01</value>   
	<value grid="a%0.9x1.25_l%0.9x1.25_oi%0.9x1.25_r%r05_m%gx1v6"	compset="AMIP_CAM40_CLM40%SP_CICE%PRES_DOCN%DOM_RTM_SGLC_SWAV"	 >1979-01-01</value> 
	<value grid="a%1.9x2.5_l%1.9x2.5_oi%1.9x2.5_r%r05_m%gx1v6"	compset="AMIP_CAM50_CLM40%SP_CICE%PRES_DOCN%DOM_RTM_SGLC_SWAV"	 >1979-01-01</value>   
	<value grid="a%1.9x2.5_l%1.9x2.5_oi%1.9x2.5_r%r05_m%gx1v6"	compset="AMIP_CAM40_CLM40%CN_CICE%PRES_DOCN%DOM_RTM_SGLC_SWAV"	 >1979-01-01</value>
      </values>
    </entry>

    <entry id="RUN_REFDIR">
      <values>
	<value grid="a%0.9x1.25_l%0.9x1.25_oi%0.9x1.25_r%r05_m%gx1v6"	compset="AMIP_CAM50_CLM40%SP_CICE%PRES_DOCN%DOM_RTM_SGLC_SWAV"	 >ccsm4_init</value>   
	<value grid="a%0.9x1.25_l%0.9x1.25_oi%0.9x1.25_r%r05_m%gx1v6"	compset="PIPD_CAM50_CLM40%SP_CICE%PRES_DOCN%DOM_RTM_SGLC_SWAV"	 >ccsm4_init</value>   
	<value grid="a%ne30np4_l%ne30np4_oi%ne30np4_r%r05_m%gx1v6"	compset="AMIP_CAM50_CLM40%SP_CICE%PRES_DOCN%DOM_RTM_SGLC_SWAV"	 >ccsm4_init</value>   
	<value grid="a%ne30np4_l%ne30np4_oi%ne30np4_r%r05_m%gx1v6"	compset="AMIP_CAM50%L60_CLM40%SP_CICE%PRES_DOCN%DOM_RTM_SGLC_SWAV">ccsm4_init</value>   
	<value grid="a%ne30np4_l%ne30np4_oi%ne30np4_r%r05_m%gx1v6"	compset="PIPD_CAM50_CLM40%SP_CICE%PRES_DOCN%DOM_RTM_SGLC_SWAV"	 >ccsm4_init</value>   
	<value grid="a%0.9x1.25_l%0.9x1.25_oi%0.9x1.25_r%r05_m%gx1v6"	compset="AMIP_CAM40_CLM40%SP_CICE%PRES_DOCN%DOM_RTM_SGLC_SWAV"	 >ccsm4_init</value> 
	<value grid="a%1.9x2.5_l%1.9x2.5_oi%1.9x2.5_r%r05_m%gx1v6"	compset="AMIP_CAM50_CLM40%SP_CICE%PRES_DOCN%DOM_RTM_SGLC_SWAV"	 >ccsm4_init</value>   
	<value grid="a%1.9x2.5_l%1.9x2.5_oi%1.9x2.5_r%r05_m%gx1v6"	compset="AMIP_CAM40_CLM40%CN_CICE%PRES_DOCN%DOM_RTM_SGLC_SWAV"	 >ccsm4_init</value>
      </values>
    </entry>

    <entry id="STOP_OPTION"> 
      <values>
	<value compset="AR95_CAM">ndays</value>
      </values>
    </entry>

    <entry id="STOP_N"> 
      <values>
	<value compset="AR95_CAM">2</value>
      </values>
    </entry>

  </entries>

</compsets>
