<?xml version="1.0"?>

<compsets>

  <!-- D compsets -->
  <compset> 
    <alias>D</alias>
    <support_level>Requires additional user-supplied datasets</support_level>
    <lname>2000_DATM%NYF_SLND_CICE_DOCN%SOM_DROF%NYF_SGLC_SWAV</lname>
  </compset>

  <compset>
    <alias>DIAF</alias>
    <support_level>Requires additional user-supplied datasets</support_level>
    <lname>2000_DATM%IAF_SLND_CICE_DOCN%SOM_DROF%IAF_SGLC_SWAV</lname>
  </compset>

  <compset>
    <alias>DTEST</alias>
    <lname>2000_DATM%NYF_SLND_CICE_DOCN%SOM_DROF%NYF_SGLC_SWAV_TEST</lname>
  </compset>

  <!-- ACME D compsets -->

  <compset>
    <alias>DTESTM</alias>
    <lname>2000_DATM%NYF_SLND_MPASCICE_DOCN%SOM_DROF%NYF_SGLC_SWAV_TEST </lname>
  </compset>

</compsets>
