<?xml version="1.0"?>
<registry model="mpas" core="sw" core_abbrev="sw" version="5.0">
	<dims>
		<dim name="nCells"/>
		<dim name="nEdges"/>
		<dim name="maxEdges"/>
		<dim name="maxEdges2"/>
		<dim name="nVertices"/>
		<dim name="TWO"                definition="2"/>
		<dim name="R3"                 definition="3"/>
		<dim name="FIFTEEN"            definition="15"/>
		<dim name="TWENTYONE"          definition="21"/>
		<dim name="vertexDegree"/>
		<dim name="nVertLevels"/>
		<dim name="nTracers"/>
	</dims>
	<nml_record name="sw_model" in_defaults="true">
		<nml_option name="config_test_case"                  type="integer"       default_value="5"/>
		<nml_option name="config_time_integration"           type="character"     default_value="RK4"/>
		<nml_option name="config_dt"                         type="real"          default_value="172.8"/>
		<nml_option name="config_calendar_type"              type="character"     default_value="gregorian_noleap"/>
		<nml_option name="config_start_time"                 type="character"     default_value="0000-01-01_00:00:00"/>
		<nml_option name="config_stop_time"                  type="character"     default_value="none"/>
		<nml_option name="config_run_duration"               type="character"     default_value="none"/>
		<nml_option name="config_stats_interval"             type="integer"       default_value="100"/>
		<nml_option name="config_h_ScaleWithMesh"            type="logical"       default_value="false"/>
		<nml_option name="config_h_mom_eddy_visc2"           type="real"          default_value="0.0"/>
		<nml_option name="config_h_mom_eddy_visc4"           type="real"          default_value="0.0"/>
		<nml_option name="config_h_tracer_eddy_diff2"        type="real"          default_value="0.0"/>
		<nml_option name="config_h_tracer_eddy_diff4"        type="real"          default_value="0.0"/>
		<nml_option name="config_thickness_adv_order"        type="integer"       default_value="2"/>
		<nml_option name="config_tracer_adv_order"           type="integer"       default_value="2"/>
		<nml_option name="config_positive_definite"          type="logical"       default_value="false"/>
		<nml_option name="config_monotonic"                  type="logical"       default_value="false"/>
		<nml_option name="config_wind_stress"                type="logical"       default_value="false"/>
		<nml_option name="config_bottom_drag"                type="logical"       default_value="false"/>
		<nml_option name="config_apvm_upwinding"             type="real"          default_value="0.5"/>
		<nml_option name="config_num_halos"                  type="integer"       default_value="2"/>
	</nml_record>
	<nml_record name="io" in_defaults="true">
		<nml_option name="config_pio_num_iotasks"            type="integer"       default_value="0"/>
		<nml_option name="config_pio_stride"                 type="integer"       default_value="1"/>
	</nml_record>
	<nml_record name="decomposition" in_defaults="true">
		<nml_option name="config_block_decomp_file_prefix"   type="character"     default_value="graph.info.part."/>
		<nml_option name="config_number_of_blocks"           type="integer"       default_value="0"/>
		<nml_option name="config_explicit_proc_decomp"       type="logical"       default_value=".false."/>
		<nml_option name="config_proc_decomp_file_prefix"    type="character"     default_value="graph.info.part."/>
	</nml_record>
	<nml_record name="restart" in_defaults="true">
		<nml_option name="config_do_restart"                 type="logical"       default_value="false"/>
	</nml_record>
	<streams>
		<stream name="input" 
				type="input"
				filename_template="grid.nc"
				filename_interval="none"
				input_interval="initial_only"
				immutable="true">

			<var name="u"/>
			<var name="h"/>
			<var name="tracers"/>
			<var name="latCell"/>
			<var name="lonCell"/>
			<var name="xCell"/>
			<var name="yCell"/>
			<var name="zCell"/>
			<var name="indexToCellID"/>
			<var name="latEdge"/>
			<var name="lonEdge"/>
			<var name="xEdge"/>
			<var name="yEdge"/>
			<var name="zEdge"/>
			<var name="indexToEdgeID"/>
			<var name="latVertex"/>
			<var name="lonVertex"/>
			<var name="xVertex"/>
			<var name="yVertex"/>
			<var name="zVertex"/>
			<var name="indexToVertexID"/>
			<var name="meshDensity"/>
			<var name="cellsOnEdge"/>
			<var name="nEdgesOnCell"/>
			<var name="nEdgesOnEdge"/>
			<var name="edgesOnCell"/>
			<var name="edgesOnEdge"/>
			<var name="weightsOnEdge"/>
			<var name="dvEdge"/>
			<var name="dcEdge"/>
			<var name="angleEdge"/>
			<var name="areaCell"/>
			<var name="areaTriangle"/>
			<var name="cellsOnCell"/>
			<var name="verticesOnCell"/>
			<var name="verticesOnEdge"/>
			<var name="edgesOnVertex"/>
			<var name="cellsOnVertex"/>
			<var name="kiteAreasOnVertex"/>
			<var name="fEdge"/>
			<var name="fVertex"/>
			<var name="fCell"/>
			<var name="h_s"/>
			<var name="boundaryEdge"/>
			<var name="boundaryVertex"/>
			<var name="boundaryCell"/>
			<var name="u_src"/>
		</stream>
		<stream name="restart" 
				type="input;output"
				filename_template="restart.$Y-$M-$D_$h.$m.$s.nc"
				filename_interval="00_00:00:01"
				input_interval="initial_only"
				output_interval="none"
				immutable="true">

			<var name="xtime"/>
			<var name="u"/>
			<var name="h"/>
			<var name="tracers"/>
			<var name="latCell"/>
			<var name="lonCell"/>
			<var name="xCell"/>
			<var name="yCell"/>
			<var name="zCell"/>
			<var name="indexToCellID"/>
			<var name="latEdge"/>
			<var name="lonEdge"/>
			<var name="xEdge"/>
			<var name="yEdge"/>
			<var name="zEdge"/>
			<var name="indexToEdgeID"/>
			<var name="latVertex"/>
			<var name="lonVertex"/>
			<var name="xVertex"/>
			<var name="yVertex"/>
			<var name="zVertex"/>
			<var name="indexToVertexID"/>
			<var name="meshDensity"/>
			<var name="meshScalingDel2"/>
			<var name="meshScalingDel4"/>
			<var name="cellsOnEdge"/>
			<var name="nEdgesOnCell"/>
			<var name="nEdgesOnEdge"/>
			<var name="edgesOnCell"/>
			<var name="edgesOnEdge"/>
			<var name="weightsOnEdge"/>
			<var name="dvEdge"/>
			<var name="dcEdge"/>
			<var name="angleEdge"/>
			<var name="areaCell"/>
			<var name="areaTriangle"/>
			<var name="cellsOnCell"/>
			<var name="verticesOnCell"/>
			<var name="verticesOnEdge"/>
			<var name="edgesOnVertex"/>
			<var name="cellsOnVertex"/>
			<var name="kiteAreasOnVertex"/>
			<var name="fEdge"/>
			<var name="fVertex"/>
			<var name="fCell"/>
			<var name="h_s"/>
			<var name="boundaryEdge"/>
			<var name="boundaryVertex"/>
			<var name="boundaryCell"/>
			<var name="u_src"/>
		</stream>
		<stream name="output" 
				type="output"
				filename_template="output.nc"
				filename_interval="none"
				output_interval="6:00:00"
				runtime_format="single_file">

			<var name="xtime"/>
			<var name="u"/>
			<var name="h"/>
			<var name="tracers"/>
			<var name="v"/>
			<var name="divergence"/>
			<var name="vorticity"/>
			<var name="vorticity_cell"/>
			<var name="pv_edge"/>
			<var name="h_edge"/>
			<var name="ke"/>
			<var name="pv_vertex"/>
			<var name="pv_cell"/>
			<var name="uReconstructX"/>
			<var name="uReconstructY"/>
			<var name="uReconstructZ"/>
			<var name="uReconstructZonal"/>
			<var name="uReconstructMeridional"/>
			<var name="latCell"/>
			<var name="lonCell"/>
			<var name="xCell"/>
			<var name="yCell"/>
			<var name="zCell"/>
			<var name="indexToCellID"/>
			<var name="latEdge"/>
			<var name="lonEdge"/>
			<var name="xEdge"/>
			<var name="yEdge"/>
			<var name="zEdge"/>
			<var name="indexToEdgeID"/>
			<var name="latVertex"/>
			<var name="lonVertex"/>
			<var name="xVertex"/>
			<var name="yVertex"/>
			<var name="zVertex"/>
			<var name="indexToVertexID"/>
			<var name="meshDensity"/>
			<var name="meshScalingDel2"/>
			<var name="meshScalingDel4"/>
			<var name="cellsOnEdge"/>
			<var name="nEdgesOnCell"/>
			<var name="nEdgesOnEdge"/>
			<var name="edgesOnCell"/>
			<var name="edgesOnEdge"/>
			<var name="weightsOnEdge"/>
			<var name="dvEdge"/>
			<var name="dcEdge"/>
			<var name="angleEdge"/>
			<var name="areaCell"/>
			<var name="areaTriangle"/>
			<var name="edgeNormalVectors"/>
			<var name="localVerticalUnitVectors"/>
			<var name="cellTangentPlane"/>
			<var name="cellsOnCell"/>
			<var name="verticesOnCell"/>
			<var name="verticesOnEdge"/>
			<var name="edgesOnVertex"/>
			<var name="cellsOnVertex"/>
			<var name="kiteAreasOnVertex"/>
			<var name="fEdge"/>
			<var name="fVertex"/>
			<var name="fCell"/>
			<var name="h_s"/>
			<var name="deriv_two"/>
			<var name="boundaryEdge"/>
			<var name="boundaryVertex"/>
			<var name="boundaryCell"/>
			<var name="u_src"/>
		</stream>
	</streams>
	<var_struct name="state" time_levs="2">
		<var name="xtime"                             type="text"     dimensions="Time"/>
		<var name="u"                                 type="real"     dimensions="nVertLevels nEdges Time"/>
		<var name="h"                                 type="real"     dimensions="nVertLevels nCells Time"/>
		<var name="tracers"                           type="real"     dimensions="nTracers nVertLevels nCells Time"/>
		<var name="v"                                 type="real"     dimensions="nVertLevels nEdges Time"/>
		<var name="divergence"                        type="real"     dimensions="nVertLevels nCells Time"/>
		<var name="vorticity"                         type="real"     dimensions="nVertLevels nVertices Time"/>
		<var name="vorticity_cell"                    type="real"     dimensions="nVertLevels nCells Time"/>
		<var name="pv_edge"                           type="real"     dimensions="nVertLevels nEdges Time"/>
		<var name="h_edge"                            type="real"     dimensions="nVertLevels nEdges Time"/>
		<var name="ke"                                type="real"     dimensions="nVertLevels nCells Time"/>
		<var name="pv_vertex"                         type="real"     dimensions="nVertLevels nVertices Time"/>
		<var name="pv_cell"                           type="real"     dimensions="nVertLevels nCells Time"/>
		<var name="uReconstructX"                     type="real"     dimensions="nVertLevels nCells Time"/>
		<var name="uReconstructY"                     type="real"     dimensions="nVertLevels nCells Time"/>
		<var name="uReconstructZ"                     type="real"     dimensions="nVertLevels nCells Time"/>
		<var name="uReconstructZonal"                 type="real"     dimensions="nVertLevels nCells Time"/>
		<var name="uReconstructMeridional"            type="real"     dimensions="nVertLevels nCells Time"/>
		<var name="vh"                                type="real"     dimensions="nVertLevels nEdges Time"/>
		<var name="circulation"                       type="real"     dimensions="nVertLevels nVertices Time"/>
		<var name="gradPVt"                           type="real"     dimensions="nVertLevels nEdges Time"/>
		<var name="gradPVn"                           type="real"     dimensions="nVertLevels nEdges Time"/>
		<var name="h_vertex"                          type="real"     dimensions="nVertLevels nVertices Time"/>
	</var_struct>
	<var_struct name="mesh" time_levs="1">
		<var name="latCell"                           type="real"     dimensions="nCells"/>
		<var name="lonCell"                           type="real"     dimensions="nCells"/>
		<var name="xCell"                             type="real"     dimensions="nCells"/>
		<var name="yCell"                             type="real"     dimensions="nCells"/>
		<var name="zCell"                             type="real"     dimensions="nCells"/>
		<var name="indexToCellID"                     type="integer"  dimensions="nCells"/>
		<var name="latEdge"                           type="real"     dimensions="nEdges"/>
		<var name="lonEdge"                           type="real"     dimensions="nEdges"/>
		<var name="xEdge"                             type="real"     dimensions="nEdges"/>
		<var name="yEdge"                             type="real"     dimensions="nEdges"/>
		<var name="zEdge"                             type="real"     dimensions="nEdges"/>
		<var name="indexToEdgeID"                     type="integer"  dimensions="nEdges"/>
		<var name="latVertex"                         type="real"     dimensions="nVertices"/>
		<var name="lonVertex"                         type="real"     dimensions="nVertices"/>
		<var name="xVertex"                           type="real"     dimensions="nVertices"/>
		<var name="yVertex"                           type="real"     dimensions="nVertices"/>
		<var name="zVertex"                           type="real"     dimensions="nVertices"/>
		<var name="indexToVertexID"                   type="integer"  dimensions="nVertices"/>
		<var name="meshDensity"                       type="real"     dimensions="nCells"/>
		<var name="meshScalingDel2"                   type="real"     dimensions="nEdges"/>
		<var name="meshScalingDel4"                   type="real"     dimensions="nEdges"/>
		<var name="cellsOnEdge"                       type="integer"  dimensions="TWO nEdges"/>
		<var name="nEdgesOnCell"                      type="integer"  dimensions="nCells"/>
		<var name="nEdgesOnEdge"                      type="integer"  dimensions="nEdges"/>
		<var name="edgesOnCell"                       type="integer"  dimensions="maxEdges nCells"/>
		<var name="edgesOnEdge"                       type="integer"  dimensions="maxEdges2 nEdges"/>
		<var name="weightsOnEdge"                     type="real"     dimensions="maxEdges2 nEdges"/>
		<var name="dvEdge"                            type="real"     dimensions="nEdges"/>
		<var name="dcEdge"                            type="real"     dimensions="nEdges"/>
		<var name="angleEdge"                         type="real"     dimensions="nEdges"/>
		<var name="areaCell"                          type="real"     dimensions="nCells"/>
		<var name="areaTriangle"                      type="real"     dimensions="nVertices"/>
		<var name="edgeNormalVectors"                 type="real"     dimensions="R3 nEdges"/>
		<var name="localVerticalUnitVectors"          type="real"     dimensions="R3 nCells"/>
		<var name="cellTangentPlane"                  type="real"     dimensions="R3 TWO nCells"/>
		<var name="cellsOnCell"                       type="integer"  dimensions="maxEdges nCells"/>
		<var name="verticesOnCell"                    type="integer"  dimensions="maxEdges nCells"/>
		<var name="verticesOnEdge"                    type="integer"  dimensions="TWO nEdges"/>
		<var name="edgesOnVertex"                     type="integer"  dimensions="vertexDegree nVertices"/>
		<var name="cellsOnVertex"                     type="integer"  dimensions="vertexDegree nVertices"/>
		<var name="kiteAreasOnVertex"                 type="real"     dimensions="vertexDegree nVertices"/>
		<var name="fEdge"                             type="real"     dimensions="nEdges"/>
		<var name="fVertex"                           type="real"     dimensions="nVertices"/>
		<var name="fCell"                             type="real"     dimensions="nCells"/>
		<var name="h_s"                               type="real"     dimensions="nCells"/>
		<var name="deriv_two"                         type="real"     dimensions="FIFTEEN TWO nEdges"/>
		<var name="advCells"                          type="integer"  dimensions="TWENTYONE nCells"/>
		<var name="defc_a"                            type="real"     dimensions="maxEdges nCells"/>
		<var name="defc_b"                            type="real"     dimensions="maxEdges nCells"/>
		<var name="kdiff"                             type="real"     dimensions="nVertLevels nCells Time"/>
		<var name="coeffs_reconstruct"                type="real"     dimensions="R3 maxEdges nCells"/>
		<var name="boundaryEdge"                      type="integer"  dimensions="nVertLevels nEdges"/>
		<var name="boundaryVertex"                    type="integer"  dimensions="nVertLevels nVertices"/>
		<var name="boundaryCell"                      type="integer"  dimensions="nVertLevels nCells"/>
		<var name="u_src"                             type="real"     dimensions="nVertLevels nEdges"/>
	</var_struct>
	<var_struct name="tend" time_levs="1">
		<var name="tend_u"                            type="real"     dimensions="nVertLevels nEdges Time"           name_in_code="u"/>
		<var name="tend_h"                            type="real"     dimensions="nVertLevels nCells Time"           name_in_code="h"/>
		<var name="tend_tracers"                      type="real"     dimensions="nTracers nVertLevels nCells Time"  name_in_code="tracers"/>
	</var_struct>
</registry>
